testmypixipkg/__init__.py
testmypixipkg/__main__.py
testmypixipkg/cli.py
testmypixipkg-0.19.0.dist-info/METADATA
testmypixipkg-0.19.0.dist-info/WHEEL
testmypixipkg-0.19.0.dist-info/entry_points.txt
testmypixipkg-0.19.0.dist-info/licenses/LICENSE
testmypixipkg-0.19.0.dist-info/RECORD
