Metadata-Version: 2.3
Name: testmypixipkg
Version: 0.19.0
Summary: Add a short description here
Project-URL: homepage, https://github.com/jjjermiah/pypackage
Project-URL: repository, https://github.com/jjjermiah/pypackage
Project-URL: documentation, https://jjjermiah.github.io/pypackage/
Project-URL: changelog, https://github.com/jjjermiah/pypackage/blob/main/docs/CHANGELOG.md
Project-URL: issues, https://github.com/jjjermiah/pypackage/issues
Author-email: Jermiah Joseph <jermiahjoseph98@gmail.com>
Maintainer-email: Jermiah Joseph <jermiahjoseph98@gmail.com>
License-Expression: MIT
License-File: LICENSE
Keywords: package,pixi,python,template,testmypixipkg
Requires-Python: >=3.11
Requires-Dist: rich
Requires-Dist: rich-click
